intake2stac/__init__.py
intake2stac/_version.py
intake2stac/cli.py
intake2stac/config_pgstac.py
intake2stac/funcs.py
intake2stac/intake2stac.py
tests/__init__.py
tests/test_intake2stac.py
INTAKE2STAC-0.6.dist-info/AUTHORS.rst
INTAKE2STAC-0.6.dist-info/LICENSE
INTAKE2STAC-0.6.dist-info/METADATA
INTAKE2STAC-0.6.dist-info/WHEEL
INTAKE2STAC-0.6.dist-info/top_level.txt
INTAKE2STAC-0.6.dist-info/RECORD
