Metadata-Version: 2.1
Name: INTAKE2STAC
Version: 0.6
Summary: A python module for creating STAC catalog from datasets in INTAKE
Home-page: https://codebase.helmholtz.cloud/CAT4KIT/intake2stac
Author: Mostafa Hadizadeh
Author-email: mostafa.hadizadeh@kit.edu
License: EUPL-1.2
Project-URL: Documentation, https://intake2stac.readthedocs.io
Project-URL: Source, https://codebase.helmholtz.cloud/CAT4KIT/intake2stac
Project-URL: Tracker, https://codebase.helmholtz.cloud/CAT4KIT/intake2stac/issues/
Keywords: CAT4KIT,KIT,EXU-Vorhaben-Research-Data-Management,helmholtz
Platform: UNKNOWN
Classifier: Environment :: Web Environment
Classifier: Intended Audience :: Developers
Classifier: License :: OSI Approved :: European Union Public Licence 1.2 (EUPL 1.2)
Classifier: Operating System :: OS Independent
Classifier: Programming Language :: Python
Classifier: Programming Language :: Python :: 3
Classifier: Programming Language :: Python :: 3 :: Only
Classifier: Programming Language :: Python :: 3.7
Classifier: Programming Language :: Python :: 3.8
Classifier: Programming Language :: Python :: 3.9
Classifier: Programming Language :: Python :: 3.10
Classifier: Topic :: Internet :: WWW/HTTP
Classifier: Topic :: Internet :: WWW/HTTP :: Dynamic Content
Classifier: Typing :: Typed
Requires-Python: >=3.7
License-File: LICENSE
License-File: AUTHORS.rst
Provides-Extra: dev
Requires-Dist: tox ; extra == 'dev'
Requires-Dist: requests ; extra == 'dev'
Requires-Dist: types-requests ; extra == 'dev'
Requires-Dist: isort (==5.9.3) ; extra == 'dev'
Requires-Dist: black (==22.3.0) ; extra == 'dev'
Requires-Dist: blackdoc (==0.3.4) ; extra == 'dev'
Requires-Dist: flake8 (==3.9.2) ; extra == 'dev'
Requires-Dist: pre-commit ; extra == 'dev'
Requires-Dist: mypy ; extra == 'dev'
Requires-Dist: pytest-django ; extra == 'dev'
Requires-Dist: pytest-cov ; extra == 'dev'
Requires-Dist: Sphinx ; extra == 'dev'
Requires-Dist: mde-sphinx-ext ; extra == 'dev'
Requires-Dist: autodocsumm ; extra == 'dev'
Requires-Dist: sphinxcontrib-django ; extra == 'dev'
Provides-Extra: testsite
Requires-Dist: tox ; extra == 'testsite'
Requires-Dist: requests ; extra == 'testsite'
Requires-Dist: types-requests ; extra == 'testsite'
Requires-Dist: isort (==5.9.3) ; extra == 'testsite'
Requires-Dist: black (==22.3.0) ; extra == 'testsite'
Requires-Dist: blackdoc (==0.3.4) ; extra == 'testsite'
Requires-Dist: flake8 (==3.9.2) ; extra == 'testsite'
Requires-Dist: pre-commit ; extra == 'testsite'
Requires-Dist: mypy ; extra == 'testsite'
Requires-Dist: pytest-django ; extra == 'testsite'
Requires-Dist: pytest-cov ; extra == 'testsite'
